codeenv.py
codeenv-0.1.1.dist-info/LICENSE
codeenv-0.1.1.dist-info/METADATA
codeenv-0.1.1.dist-info/WHEEL
codeenv-0.1.1.dist-info/top_level.txt
codeenv-0.1.1.dist-info/RECORD
