Metadata-Version: 2.1
Name: codeenv
Version: 0.1.1
Summary: Automatic coding environment generator for basic development
Author-email: Rares Sarmasag <rares.sarmasag@stud.acs.upb.ro>
License: Eclipse Public License - v 2.0
Project-URL: Home, https://github.com/rares9301/codeenv
License-File: LICENSE
Requires-Dist: gitpython >=3.1.24
